StockDataInterface/StockDataInterface.py
StockDataInterface/__init__.py
StockDataInterface/api.py
StockDataInterface/source.py
stock-data-interface/StockDataInterface.py
stock-data-interface/__init__.py
StockDataInterface-1.1.8.dist-info/LICENSE
StockDataInterface-1.1.8.dist-info/METADATA
StockDataInterface-1.1.8.dist-info/WHEEL
StockDataInterface-1.1.8.dist-info/top_level.txt
StockDataInterface-1.1.8.dist-info/RECORD
